MANIFEST.in
README.md
setup.cfg
setup.py
pycollatinus/__init__.py
pycollatinus/ch.py
pycollatinus/error.py
pycollatinus/irregs.py
pycollatinus/lemmatiseur.py
pycollatinus/lemme.py
pycollatinus/modele.py
pycollatinus/parser.py
pycollatinus/util.py
pycollatinus.egg-info/PKG-INFO
pycollatinus.egg-info/SOURCES.txt
pycollatinus.egg-info/dependency_links.txt
pycollatinus.egg-info/not-zip-safe
pycollatinus.egg-info/requires.txt
pycollatinus.egg-info/top_level.txt
pycollatinus/data/assimilations.la
pycollatinus/data/contractions.la
pycollatinus/data/hyphen.la
pycollatinus/data/irregs.la
pycollatinus/data/lem_ext.la
pycollatinus/data/lemmes.la
pycollatinus/data/modeles.la
pycollatinus/data/morphos.fr
pycollatinus/data/tags.la