Metadata-Version: 1.0
Name: pycollatinus
Version: 0.1.6
Summary: Collatinus Port for Python
Home-page: https://github.com/ponteineptique/collatinus-python
Author: Thibault Clerice, Yves Ouvrard, Philippe Verkerk
Author-email: leponteineptique@gmail.com
License: GNU GPL v2
Platform: UNKNOWN
